COPYING
COPYING.LESSER
README
setup.py
examples/scxml_sandbox/SCXMLEventProcessor.js
examples/scxml_sandbox/default_doc.xml
examples/scxml_sandbox/example_list.json
examples/scxml_sandbox/index.html
examples/scxml_sandbox/safe_eval.py
examples/scxml_sandbox/sandbox.js
examples/scxml_sandbox/sandbox_server.xml
examples/scxml_sandbox/server.py
examples/scxml_sandbox/styles.css
examples/scxml_sandbox/example_docs/echo.scxml
examples/scxml_sandbox/example_docs/echo_sender.xml
examples/scxml_sandbox/example_docs/factorial.xml
examples/scxml_sandbox/example_docs/invoke.xml
examples/scxml_sandbox/example_docs/parallel2.xml
examples/scxml_sandbox/example_docs/parallel5.xml
examples/scxml_sandbox/example_docs/preemption/preempted.xml
examples/scxml_sandbox/example_docs/preemption/testPreemption.scxml
examples/scxml_sandbox/img/logo1.png
examples/scxml_sandbox/img/spider.png
examples/scxml_sandbox/img/browsers/background_browser.gif
examples/scxml_sandbox/img/browsers/browser_chrome.gif
examples/scxml_sandbox/img/browsers/browser_firefox.gif
examples/scxml_sandbox/img/browsers/browser_gcf.gif
examples/scxml_sandbox/img/browsers/browser_msie.gif
examples/scxml_sandbox/img/browsers/browser_opera.gif
examples/scxml_sandbox/img/browsers/browser_safari.gif
examples/scxml_sandbox/lib/jquery-ui.min.js
examples/scxml_sandbox/lib/jquery.ba-bbq.min.js
examples/scxml_sandbox/lib/jquery.format.js
examples/scxml_sandbox/lib/jquery.jLog.min.js
examples/scxml_sandbox/lib/jquery.js
examples/scxml_sandbox/lib/jquery.reject.min.js
examples/scxml_sandbox/lib/jquery.tmpl.js
examples/scxml_sandbox/lib/codemirror/lib/codemirror.css
examples/scxml_sandbox/lib/codemirror/lib/codemirror.js
examples/scxml_sandbox/lib/codemirror/lib/overlay.js
examples/scxml_sandbox/lib/codemirror/lib/runmode.js
examples/scxml_sandbox/lib/codemirror/mode/clike/clike.js
examples/scxml_sandbox/lib/codemirror/mode/clike/index.html
examples/scxml_sandbox/lib/codemirror/mode/clojure/clojure.js
src/pyscxml.egg-info/PKG-INFO
src/pyscxml.egg-info/SOURCES.txt
src/pyscxml.egg-info/dependency_links.txt
src/pyscxml.egg-info/requires.txt
src/pyscxml.egg-info/top_level.txt
