Metadata-Version: 1.0
Name: pyscxml
Version: 0.8.3-20120108
Summary: A pure Python SCXML parser/interpreter
Home-page: http://code.google.com/p/pyscxml/
Author: Johan Roxendal
Author-email: johan@roxendal.com
License: LGPLv3
Download-URL: http://code.google.com/p/pyscxml/downloads/list?q=full
Platform: UNKNOWN
Classifier: Development Status :: 4 - Beta
Classifier: Environment :: Console
Classifier: Environment :: Web Environment
Classifier: Intended Audience :: Developers
Classifier: License :: OSI Approved :: GNU Library or Lesser General Public License (LGPL)
Classifier: Operating System :: OS Independent
Classifier: Programming Language :: Python
Classifier: Topic :: Communications :: Telephony
Classifier: Topic :: Internet :: WWW/HTTP
Classifier: Topic :: Internet :: WWW/HTTP :: WSGI
Classifier: Topic :: Software Development :: Interpreters
Classifier: Topic :: Software Development :: Libraries :: Python Modules
Classifier: Topic :: Text Processing :: Markup :: XML
